seoaudit/__init__.py
seoaudit/__main__.py
seoaudit/config.py
seoaudit/analyzer/__init__.py
seoaudit/analyzer/page_parser.py
seoaudit/analyzer/seo_auditor.py
seoaudit/analyzer/site_parser.py
seoaudit/checks/__init__.py
seoaudit/checks/element.py
seoaudit/checks/page.py
seoaudit/checks/site.py
seoaudit-0.0.1.dev3.dist-info/LICENSE.txt
seoaudit-0.0.1.dev3.dist-info/METADATA
seoaudit-0.0.1.dev3.dist-info/WHEEL
seoaudit-0.0.1.dev3.dist-info/entry_points.txt
seoaudit-0.0.1.dev3.dist-info/top_level.txt
seoaudit-0.0.1.dev3.dist-info/RECORD
