Metadata-Version: 2.1
Name: seoaudit
Version: 0.0.1.dev3
Summary: Run SEO checks on a set of urls.
Home-page: https://github.com/Guber/seoaudit
Author: Emanuel Guberovic
Author-email: emanuel.guberovic@gmail.com
License: MIT
Classifier: License :: OSI Approved :: MIT License
Classifier: Programming Language :: Python
Classifier: Programming Language :: Python :: 3
Classifier: Programming Language :: Python :: 3.6
Classifier: Programming Language :: Python :: Implementation :: CPython
Classifier: Programming Language :: Python :: Implementation :: PyPy
Requires-Python: >=3.6.0
License-File: LICENSE.txt
Requires-Dist: requests
Requires-Dist: lxml
Requires-Dist: nltk
Requires-Dist: extruct
Requires-Dist: selenium
Requires-Dist: json2html
Provides-Extra: selenium_parser_feature
Requires-Dist: selenium ; extra == 'selenium_parser_feature'
